main/__init__.py
main/cil.py
main/manager.py
pm2fpy-0.1.1.dist-info/METADATA
pm2fpy-0.1.1.dist-info/WHEEL
pm2fpy-0.1.1.dist-info/entry_points.txt
pm2fpy-0.1.1.dist-info/RECORD
