Metadata-Version: 2.4
Name: pm2fpy
Version: 0.1.1
Summary: Simple Python daemon manager like pm2
Author-email: YourName <youremail@example.com>
License: MIT
Keywords: daemon,pm2,process,python
Classifier: Operating System :: OS Independent
Classifier: Programming Language :: Python :: 3
Requires-Python: >=3.6
Requires-Dist: psutil
Requires-Dist: tabulate
